patio_redis.py
patio_redis-0.1.1.dist-info/COPYING
patio_redis-0.1.1.dist-info/METADATA
patio_redis-0.1.1.dist-info/WHEEL
patio_redis-0.1.1.dist-info/RECORD
